Metadata-Version: 2.1
Name: pinyinTools
Version: 1.0.1
Summary: Python拼音小工具/Python Pinyin gadget
Home-page: https://yangguang-gongzuoshi.top/wry/
Author: Ruoyu Wang
Author-email: wry2022@outlook.com
License: MIT License
Platform: UNKNOWN
Requires: pypinyin
